[
  { "id": "B1 CHEDDAR", "nombre": "B1 CHEDDAR", "precio": 8200.0, "descripcion": "Burguer y queso gouda o cheddar", "subcategoria": "Burger", "contieneModificadores": true, "zonaFranca": true, "localCentral": false, "imagen": "B1.jpg", "agregados": [] },
  { "id": "B2", "nombre": "B2", "precio": 9600.0, "descripcion": "Queso Gouda, lechuga, tomate, cebolla morada y huevo frito", "subcategoria": "Burger", "contieneModificadores": true, "zonaFranca": true, "localCentral": false, "imagen": "B2.jpg", "agregados": [] },
  { "id": "B3", "nombre": "B3", "precio": 10900.0, "descripcion": "Burger con queso cheddar, tocino, huevo frito, pepinillos y salsa BBQ", "subcategoria": "Burger", "contieneModificadores": false, "zonaFranca": true, "localCentral": false, "imagen": "B3.jpg", "agregados": [] },
  { "id": "B4", "nombre": "B4", "precio": 10400.0, "descripcion": "Burger con camarones al limón y palta trozada", "subcategoria": "Burger", "contieneModificadores": false, "zonaFranca": true, "localCentral": false, "imagen": "B4.jpg", "agregados": [] },
  {
      "id": "S1 TLT",
      "nombre": "S1 TLT",
      "precio": 9200.0,
      "descripcion": "BAGUETTE DE TOCINO + LECHUGA + TOMATE",
      "subcategoria": "Sandwich",
      "contieneModificadores": false,
      "zonaFranca": true,
      "localCentral": false,
      "imagen": "S1.jpg",
      "agregados": []
  },
  {
      "id": "K1",
      "nombre": "K1 Aros de Cebolla",
      "precio": 5500.0,
      "descripcion": "AROS DE CEBOLLA APANADOS (15U.)",
      "subcategoria": "Snack",
      "contieneModificadores": false,
      "zonaFranca": true,
      "localCentral": false,
      "imagen": "K1.jpg",
      "agregados": []
  },
  {
      "id": "GASEOSA1",
      "nombre": "Gaseosa Coca-Cola",
      "precio": 2500.0,
      "descripcion": "Lata 350ml",
      "subcategoria": "Bebida",
      "contieneModificadores": false,
      "zonaFranca": true,
      "localCentral": false,
      "imagen": "coca_cola.jpg",
      "agregados": []
  },
  {
      "id": "AGUA1",
      "nombre": "Agua sin Gas",
      "precio": 2000.0,
      "descripcion": "Botella 500ml",
      "subcategoria": "Bebida",
      "contieneModificadores": false,
      "zonaFranca": true,
      "localCentral": false,
      "imagen": "agua_sin_gas.jpg",
      "agregados": []
  }
]